.gitignore
INSTALL
LICENSE
NEWS
README
setup.cfg
setup.py
WsgiService.egg-info/PKG-INFO
WsgiService.egg-info/SOURCES.txt
WsgiService.egg-info/dependency_links.txt
WsgiService.egg-info/requires.txt
WsgiService.egg-info/top_level.txt
docs/Makefile
docs/conf.py
docs/http.rst
docs/index.rst
docs/philosophy.rst
docs/todo.rst
docs/tutorial.rst
docs/modules/reference.rst
examples/README
examples/store.py
examples/store_gzipped.py
examples/user.py
tests/test_application.py
tests/test_resource.py
tests/test_resource_json.py
tests/test_router.py
tests/test_xmlserializer.py
wsgiservice/__init__.py
wsgiservice/application.py
wsgiservice/decorators.py
wsgiservice/exceptions.py
wsgiservice/resource.py
wsgiservice/routing.py
wsgiservice/status.py
wsgiservice/xmlserializer.py