Metadata-Version: 1.1
Name: WsgiService
Version: 0.4.0
Summary: A lean WSGI framework for easy creation of REST services
Home-page: http://github.com/pneff/wsgiservice/tree/master
Author: Patrice Neff <software@patrice.ch>
Author-email: UNKNOWN
License: BSD
Download-URL: http://pypi.python.org/pypi/WsgiService
Platform: UNKNOWN
Classifier: Development Status :: 5 - Production/Stable
Classifier: Environment :: Web Environment
Classifier: Intended Audience :: Developers
Classifier: License :: OSI Approved :: BSD License
Classifier: Programming Language :: Python :: 2.6
Classifier: Programming Language :: Python :: 2.7
Classifier: Topic :: Internet :: WWW/HTTP :: WSGI :: Application
